tess_ephem/__init__.py
tess_ephem/angle.py
tess_ephem/ephem.py
tess_ephem-0.6.3.dist-info/LICENSE
tess_ephem-0.6.3.dist-info/METADATA
tess_ephem-0.6.3.dist-info/WHEEL
tess_ephem-0.6.3.dist-info/RECORD
