Metadata-Version: 2.1
Name: tess-ephem
Version: 0.6.3
Summary: Where are Solar System objects located in TESS FFI data?
Home-page: https://github.com/SSDataLab/tess-ephem
License: MIT
Keywords: NASA, TESS, Astronomy
Author: Geert Barentsen
Author-email: hello@geert.io
Requires-Python: >=3.9,<4.0
Classifier: Intended Audience :: Science/Research
Classifier: License :: OSI Approved :: MIT License
Classifier: Programming Language :: Python :: 3
Classifier: Programming Language :: Python :: 3.9
Classifier: Programming Language :: Python :: 3.10
Classifier: Programming Language :: Python :: 3.11
Classifier: Programming Language :: Python :: 3.12
Classifier: Topic :: Scientific/Engineering :: Astronomy
Requires-Dist: astropy (>=5.2.0,<6.0.0)
Requires-Dist: astroquery (>=0.4.9,<0.5.0)
Requires-Dist: numpy (>=1.23.0,<2.0.0)
Requires-Dist: pandas (>=2.0,<3.0)
Requires-Dist: scipy (>=1.9.0,<2.0.0)
Requires-Dist: tesswcs (>=1.7.0,<2.0.0)
Project-URL: Repository, https://github.com/SSDataLab/tess-ephem
